unitycatalog/ai/llama_index/__init__.py
unitycatalog/ai/llama_index/toolkit.py
unitycatalog/ai/llama_index/version.py
unitycatalog_llamaindex-0.2.0.dist-info/METADATA
unitycatalog_llamaindex-0.2.0.dist-info/WHEEL
unitycatalog_llamaindex-0.2.0.dist-info/RECORD
