Metadata-Version: 2.4
Name: unitycatalog-llamaindex
Version: 0.2.0
Summary: Support for Unity Catalog functions as LlamaIndex tools
Author-email: Ben Wilson <benjamin.wilson@databricks.com>
License: Apache-2.0
Requires-Python: >=3.9
Requires-Dist: llama-index>=0.11.0
Requires-Dist: unitycatalog-ai
Provides-Extra: databricks
Requires-Dist: unitycatalog-ai[databricks]; extra == 'databricks'
Provides-Extra: databricks-dev
Requires-Dist: unitycatalog-ai[databricks-dev]; extra == 'databricks-dev'
Provides-Extra: dev
Requires-Dist: unitycatalog-ai[dev]; extra == 'dev'
